MANIFEST.in
README.md
requirements.txt
setup.py
byteplus_rec/__init__.py
byteplus_rec/__version__.py
byteplus_rec.egg-info/PKG-INFO
byteplus_rec.egg-info/SOURCES.txt
byteplus_rec.egg-info/dependency_links.txt
byteplus_rec.egg-info/requires.txt
byteplus_rec.egg-info/top_level.txt
byteplus_rec/content/__init__.py
byteplus_rec/content/abstract_client.py
byteplus_rec/content/constant.py
byteplus_rec/content/content_client.py
byteplus_rec/content/content_client_builder.py
byteplus_rec/content/example/__init__.py
byteplus_rec/content/example/main.py
byteplus_rec/content/example/mock_helper.py
byteplus_rec/content/protocol/__init__.py
byteplus_rec/content/protocol/byteplus_saas_content_pb2.py
byteplus_rec/region/__init__.py
byteplus_rec/region/region.py
byteplus_rec/retail/__init__.py
byteplus_rec/retail/abstract_client.py
byteplus_rec/retail/constant.py
byteplus_rec/retail/retail_client.py
byteplus_rec/retail/retail_client_builder.py
byteplus_rec/retail/example/__init__.py
byteplus_rec/retail/example/main.py
byteplus_rec/retail/example/mock_helper.py
byteplus_rec/retail/protocol/__init__.py
byteplus_rec/retail/protocol/byteplus_saas_retail_pb2.py